readline0.py
readline0-1.0.dist-info/COPYING
readline0-1.0.dist-info/METADATA
readline0-1.0.dist-info/WHEEL
readline0-1.0.dist-info/top_level.txt
readline0-1.0.dist-info/RECORD
