Metadata-Version: 2.1
Name: readline0
Version: 1.0
Summary: Pure Python, relatively-efficient reading of null-terminated lines
Home-page: https://stromberg.dnsalias.org/~strombrg/readline0.html
Author: Daniel Richard Stromberg
Author-email: strombrg@gmail.com
License: Apache v2
Keywords: text lines delimiter
Platform: Cross platform
Classifier: Development Status :: 5 - Production/Stable
Classifier: Intended Audience :: Developers
Classifier: Programming Language :: Python :: 2
Classifier: Programming Language :: Python :: 3
